<?xml version="1.0" encoding="UTF-8" standalone="no"?>
<!DOCTYPE Almacen SYSTEM "Almacen.dtd">
<Almacen>
          <Productos>
                    <Producto Codigo="123">
                              <Nombre>f</Nombre>
                              <Descripcion>f</Descripcion>
                              <Stock>f</Stock>
                              <Pendientes>f</Pendientes>
                              <Localizacion>
                                        <Pasillo>f</Pasillo>
                                        <Estanteria>f</Estanteria>
                                        <Estante>f</Estante>
                              </Localizacion>
                    </Producto>
          </Productos>
          <Clientes>
                    <Cliente Id="1234">
                              <Nombre>1234</Nombre>
                              <Apellidos>f</Apellidos>
                              <Email>f</Email>
                              <Telefono>f</Telefono>
                              <Direccion>
                                        <Calle>f</Calle>
                                        <Numero>f</Numero>
                                        <CodigoPostal>f</CodigoPostal>
                                        <Poblacion>f</Poblacion>
                                        <Pais>f</Pais>
                              </Direccion>
                    </Cliente>
          </Clientes>
          <Pedidos>
                    <Pedido Id="12345">
                              <Producto Código="f">
                                        <Info>f</Info>
                                        <Cantidad>f</Cantidad>
                              </Producto>
                              <Destinatario>f</Destinatario>
                              <Fecha>f</Fecha>
                              <Direccion>
                                        <Calle>f</Calle>
                                        <Numero>f</Numero>
                                        <CodigoPostal>f</CodigoPostal>
                                        <Poblacion>f</Poblacion>
                                        <Pais>f</Pais>
                              </Direccion>
                    </Pedido>
          </Pedidos>
</Almacen>
